<?xml version="1.0" encoding="UTF-8"?>

<!-- generated on 2023-11-06 05:19:06 by Eclipse SUMO sumo Version v1_18_0+2427-ccfd716261e
<configuration xmlns:xsi="http://www.w3.org/2001/XMLSchema-instance" xsi:noNamespaceSchemaLocation="http://sumo.dlr.de/xsd/sumoConfiguration.xsd">

    <input>
        <net-file value="C:\Users\delphi\testreports\sumoExtra\git\tools\game\square/square.net.xml"/>
        <additional-files value="C:\Users\delphi\testreports\sumoExtra\git\tools\game\square/square.tll.xml.delay_based,C:\Users\delphi\testreports\sumoExtra\git\tools\game\square/square.poi.xml,C:\Users\delphi\testreports\sumoExtra\git\tools\game\square/square.rou.xml,C:\Users\delphi\testreports\sumoExtra\git\tools\game\input_additional.add.xml"/>
    </input>

    <output>
        <human-readable-time value="false"/>
        <tripinfo-output value="C:\Users\delphi\testreports\sumoExtra\git\tools\game\tripinfos.xml"/>
        <tripinfo-output.write-unfinished value="true"/>
        <tripinfo-output.write-undeparted value="true"/>
        <statistic-output value="C:\Users\delphi\testreports\sumoExtra\git\tools\game\square.stats.xml"/>
    </output>

    <time>
        <begin value="0"/>
        <end value="180"/>
        <step-length value=".1"/>
    </time>

    <report>
        <verbose value="false"/>
        <xml-validation value="never"/>
        <no-warnings value="true"/>
        <duration-log.statistics value="true"/>
        <no-step-log value="true"/>
    </report>

    <gui_only>
        <gui-settings-file value="C:\Users\delphi\testreports\sumoExtra\git\tools\game\square/settings.xml"/>
    </gui_only>

</configuration>
-->

<tlsStates xmlns:xsi="http://www.w3.org/2001/XMLSchema-instance" xsi:noNamespaceSchemaLocation="http://sumo.dlr.de/xsd/tlsstates_file.xsd">
    <tlsState time="0.00" id="A0" programID="manual" phase="0" state="uuuuyyyyuuuuyyyy"/>
    <tlsState time="0.00" id="B0" programID="manual" phase="0" state="uuuuyyyyuuuuyyyy"/>
    <tlsState time="0.00" id="left0" programID="0" phase="0" state="G"/>
    <tlsState time="0.00" id="top1" programID="0" phase="0" state="G"/>
    <tlsState time="0.00" id="bottom1" programID="0" phase="0" state="G"/>
    <tlsState time="0.00" id="A1" programID="manual" phase="0" state="uuuuyyyyuuuuyyyy"/>
    <tlsState time="0.00" id="bottom0" programID="0" phase="0" state="G"/>
    <tlsState time="0.00" id="top0" programID="0" phase="0" state="G"/>
    <tlsState time="0.00" id="right1" programID="0" phase="0" state="G"/>
    <tlsState time="0.00" id="B1" programID="manual" phase="0" state="uuuuyyyyuuuuyyyy"/>
    <tlsState time="0.00" id="right0" programID="0" phase="0" state="G"/>
    <tlsState time="0.00" id="left1" programID="0" phase="0" state="G"/>
    <tlsState time="1.00" id="A0" programID="manual" phase="1" state="uuuurrrruuuurrrr"/>
    <tlsState time="1.00" id="B0" programID="manual" phase="1" state="uuuurrrruuuurrrr"/>
    <tlsState time="1.00" id="B1" programID="manual" phase="1" state="uuuurrrruuuurrrr"/>
    <tlsState time="1.00" id="A1" programID="manual" phase="1" state="uuuurrrruuuurrrr"/>
    <tlsState time="2.00" id="A0" programID="manual" phase="2" state="GGggrrrrGGggrrrr"/>
    <tlsState time="2.00" id="B0" programID="manual" phase="2" state="GGggrrrrGGggrrrr"/>
    <tlsState time="2.00" id="A1" programID="manual" phase="2" state="GGggrrrrGGggrrrr"/>
    <tlsState time="2.00" id="B1" programID="manual" phase="2" state="GGggrrrrGGggrrrr"/>
    <tlsState time="7.00" id="B1" programID="manual" phase="3" state="yyyyuuuuyyyyuuuu"/>
    <tlsState time="8.00" id="B1" programID="manual" phase="4" state="rrrruuuurrrruuuu"/>
    <tlsState time="9.00" id="B0" programID="manual" phase="3" state="yyyyuuuuyyyyuuuu"/>
    <tlsState time="9.00" id="B1" programID="manual" phase="5" state="rrrrGGggrrrrGGgg"/>
    <tlsState time="10.00" id="B0" programID="manual" phase="4" state="rrrruuuurrrruuuu"/>
    <tlsState time="10.00" id="A1" programID="manual" phase="3" state="yyyyuuuuyyyyuuuu"/>
    <tlsState time="11.00" id="B0" programID="manual" phase="5" state="rrrrGGggrrrrGGgg"/>
    <tlsState time="11.00" id="A1" programID="manual" phase="4" state="rrrruuuurrrruuuu"/>
    <tlsState time="12.00" id="B0" programID="manual" phase="0" state="uuuuyyyyuuuuyyyy"/>
    <tlsState time="12.00" id="A1" programID="manual" phase="5" state="rrrrGGggrrrrGGgg"/>
    <tlsState time="13.00" id="A0" programID="manual" phase="3" state="yyyyuuuuyyyyuuuu"/>
    <tlsState time="13.00" id="B0" programID="manual" phase="1" state="uuuurrrruuuurrrr"/>
    <tlsState time="13.00" id="A1" programID="manual" phase="0" state="uuuuyyyyuuuuyyyy"/>
    <tlsState time="14.00" id="A0" programID="manual" phase="4" state="rrrruuuurrrruuuu"/>
    <tlsState time="14.00" id="B0" programID="manual" phase="2" state="GGggrrrrGGggrrrr"/>
    <tlsState time="14.00" id="A1" programID="manual" phase="1" state="uuuurrrruuuurrrr"/>
    <tlsState time="15.00" id="A0" programID="manual" phase="5" state="rrrrGGggrrrrGGgg"/>
    <tlsState time="15.00" id="B0" programID="manual" phase="3" state="yyyyuuuuyyyyuuuu"/>
    <tlsState time="15.00" id="A1" programID="manual" phase="2" state="GGggrrrrGGggrrrr"/>
    <tlsState time="16.00" id="A0" programID="manual" phase="0" state="uuuuyyyyuuuuyyyy"/>
    <tlsState time="16.00" id="B0" programID="manual" phase="4" state="rrrruuuurrrruuuu"/>
    <tlsState time="16.00" id="A1" programID="manual" phase="3" state="yyyyuuuuyyyyuuuu"/>
    <tlsState time="17.00" id="A0" programID="manual" phase="1" state="uuuurrrruuuurrrr"/>
    <tlsState time="17.00" id="B0" programID="manual" phase="5" state="rrrrGGggrrrrGGgg"/>
    <tlsState time="17.00" id="A1" programID="manual" phase="4" state="rrrruuuurrrruuuu"/>
    <tlsState time="18.00" id="A0" programID="manual" phase="2" state="GGggrrrrGGggrrrr"/>
    <tlsState time="18.00" id="A1" programID="manual" phase="5" state="rrrrGGggrrrrGGgg"/>
    <tlsState time="19.00" id="A0" programID="manual" phase="3" state="yyyyuuuuyyyyuuuu"/>
    <tlsState time="20.00" id="A0" programID="manual" phase="4" state="rrrruuuurrrruuuu"/>
    <tlsState time="20.50" id="B0" programID="manual" phase="0" state="uuuuyyyyuuuuyyyy"/>
    <tlsState time="21.00" id="A0" programID="manual" phase="5" state="rrrrGGggrrrrGGgg"/>
    <tlsState time="21.50" id="B0" programID="manual" phase="1" state="uuuurrrruuuurrrr"/>
    <tlsState time="22.00" id="A0" programID="manual" phase="0" state="uuuuyyyyuuuuyyyy"/>
    <tlsState time="22.00" id="A1" programID="manual" phase="0" state="uuuuyyyyuuuuyyyy"/>
    <tlsState time="22.50" id="B0" programID="manual" phase="2" state="GGggrrrrGGggrrrr"/>
    <tlsState time="23.00" id="A0" programID="manual" phase="1" state="uuuurrrruuuurrrr"/>
    <tlsState time="23.00" id="A1" programID="manual" phase="1" state="uuuurrrruuuurrrr"/>
    <tlsState time="24.00" id="A0" programID="manual" phase="2" state="GGggrrrrGGggrrrr"/>
    <tlsState time="24.00" id="A1" programID="manual" phase="2" state="GGggrrrrGGggrrrr"/>
    <tlsState time="25.00" id="A1" programID="manual" phase="3" state="yyyyuuuuyyyyuuuu"/>
    <tlsState time="25.40" id="A0" programID="manual" phase="3" state="yyyyuuuuyyyyuuuu"/>
    <tlsState time="26.00" id="B0" programID="manual" phase="3" state="yyyyuuuuyyyyuuuu"/>
    <tlsState time="26.00" id="A1" programID="manual" phase="4" state="rrrruuuurrrruuuu"/>
    <tlsState time="26.40" id="A0" programID="manual" phase="4" state="rrrruuuurrrruuuu"/>
    <tlsState time="27.00" id="B0" programID="manual" phase="4" state="rrrruuuurrrruuuu"/>
    <tlsState time="27.00" id="A1" programID="manual" phase="5" state="rrrrGGggrrrrGGgg"/>
    <tlsState time="27.00" id="B1" programID="manual" phase="0" state="uuuuyyyyuuuuyyyy"/>
    <tlsState time="27.40" id="A0" programID="manual" phase="5" state="rrrrGGggrrrrGGgg"/>
    <tlsState time="28.00" id="B0" programID="manual" phase="5" state="rrrrGGggrrrrGGgg"/>
    <tlsState time="28.00" id="B1" programID="manual" phase="1" state="uuuurrrruuuurrrr"/>
    <tlsState time="28.00" id="A1" programID="manual" phase="0" state="uuuuyyyyuuuuyyyy"/>
    <tlsState time="29.00" id="A1" programID="manual" phase="1" state="uuuurrrruuuurrrr"/>
    <tlsState time="29.00" id="B1" programID="manual" phase="2" state="GGggrrrrGGggrrrr"/>
    <tlsState time="30.00" id="A1" programID="manual" phase="2" state="GGggrrrrGGggrrrr"/>
    <tlsState time="30.00" id="B1" programID="manual" phase="3" state="yyyyuuuuyyyyuuuu"/>
    <tlsState time="31.00" id="B1" programID="manual" phase="4" state="rrrruuuurrrruuuu"/>
    <tlsState time="32.00" id="B1" programID="manual" phase="5" state="rrrrGGggrrrrGGgg"/>
    <tlsState time="33.00" id="B1" programID="manual" phase="0" state="uuuuyyyyuuuuyyyy"/>
    <tlsState time="34.00" id="B1" programID="manual" phase="1" state="uuuurrrruuuurrrr"/>
    <tlsState time="34.50" id="A1" programID="manual" phase="3" state="yyyyuuuuyyyyuuuu"/>
    <tlsState time="35.00" id="B1" programID="manual" phase="2" state="GGggrrrrGGggrrrr"/>
    <tlsState time="35.50" id="A1" programID="manual" phase="4" state="rrrruuuurrrruuuu"/>
    <tlsState time="36.50" id="A1" programID="manual" phase="5" state="rrrrGGggrrrrGGgg"/>
    <tlsState time="36.70" id="B0" programID="manual" phase="0" state="uuuuyyyyuuuuyyyy"/>
    <tlsState time="37.50" id="A1" programID="manual" phase="0" state="uuuuyyyyuuuuyyyy"/>
    <tlsState time="37.70" id="B0" programID="manual" phase="1" state="uuuurrrruuuurrrr"/>
    <tlsState time="38.50" id="A0" programID="manual" phase="0" state="uuuuyyyyuuuuyyyy"/>
    <tlsState time="38.50" id="A1" programID="manual" phase="1" state="uuuurrrruuuurrrr"/>
    <tlsState time="38.60" id="B1" programID="manual" phase="3" state="yyyyuuuuyyyyuuuu"/>
    <tlsState time="38.70" id="B0" programID="manual" phase="2" state="GGggrrrrGGggrrrr"/>
    <tlsState time="39.50" id="A0" programID="manual" phase="1" state="uuuurrrruuuurrrr"/>
    <tlsState time="39.50" id="A1" programID="manual" phase="2" state="GGggrrrrGGggrrrr"/>
    <tlsState time="39.60" id="B1" programID="manual" phase="4" state="rrrruuuurrrruuuu"/>
    <tlsState time="39.70" id="B0" programID="manual" phase="3" state="yyyyuuuuyyyyuuuu"/>
    <tlsState time="40.50" id="A0" programID="manual" phase="2" state="GGggrrrrGGggrrrr"/>
    <tlsState time="40.50" id="A1" programID="manual" phase="3" state="yyyyuuuuyyyyuuuu"/>
    <tlsState time="40.60" id="B1" programID="manual" phase="5" state="rrrrGGggrrrrGGgg"/>
    <tlsState time="40.70" id="B0" programID="manual" phase="4" state="rrrruuuurrrruuuu"/>
    <tlsState time="41.50" id="A0" programID="manual" phase="3" state="yyyyuuuuyyyyuuuu"/>
    <tlsState time="41.50" id="A1" programID="manual" phase="4" state="rrrruuuurrrruuuu"/>
    <tlsState time="41.70" id="B0" programID="manual" phase="5" state="rrrrGGggrrrrGGgg"/>
    <tlsState time="42.50" id="A0" programID="manual" phase="4" state="rrrruuuurrrruuuu"/>
    <tlsState time="42.50" id="A1" programID="manual" phase="5" state="rrrrGGggrrrrGGgg"/>
    <tlsState time="42.60" id="B1" programID="manual" phase="0" state="uuuuyyyyuuuuyyyy"/>
    <tlsState time="42.70" id="B0" programID="manual" phase="0" state="uuuuyyyyuuuuyyyy"/>
    <tlsState time="43.50" id="A0" programID="manual" phase="5" state="rrrrGGggrrrrGGgg"/>
    <tlsState time="43.50" id="A1" programID="manual" phase="0" state="uuuuyyyyuuuuyyyy"/>
    <tlsState time="43.60" id="B1" programID="manual" phase="1" state="uuuurrrruuuurrrr"/>
    <tlsState time="43.70" id="B0" programID="manual" phase="1" state="uuuurrrruuuurrrr"/>
    <tlsState time="44.50" id="A1" programID="manual" phase="1" state="uuuurrrruuuurrrr"/>
    <tlsState time="44.60" id="B1" programID="manual" phase="2" state="GGggrrrrGGggrrrr"/>
    <tlsState time="44.70" id="B0" programID="manual" phase="2" state="GGggrrrrGGggrrrr"/>
    <tlsState time="45.50" id="A1" programID="manual" phase="2" state="GGggrrrrGGggrrrr"/>
    <tlsState time="46.20" id="B0" programID="manual" phase="3" state="yyyyuuuuyyyyuuuu"/>
    <tlsState time="46.50" id="A1" programID="manual" phase="3" state="yyyyuuuuyyyyuuuu"/>
    <tlsState time="46.60" id="B1" programID="manual" phase="3" state="yyyyuuuuyyyyuuuu"/>
    <tlsState time="47.20" id="B0" programID="manual" phase="4" state="rrrruuuurrrruuuu"/>
    <tlsState time="47.50" id="A1" programID="manual" phase="4" state="rrrruuuurrrruuuu"/>
    <tlsState time="47.60" id="B1" programID="manual" phase="4" state="rrrruuuurrrruuuu"/>
    <tlsState time="48.20" id="B0" programID="manual" phase="5" state="rrrrGGggrrrrGGgg"/>
    <tlsState time="48.50" id="A1" programID="manual" phase="5" state="rrrrGGggrrrrGGgg"/>
    <tlsState time="48.60" id="B1" programID="manual" phase="5" state="rrrrGGggrrrrGGgg"/>
    <tlsState time="49.50" id="A1" programID="manual" phase="0" state="uuuuyyyyuuuuyyyy"/>
    <tlsState time="49.60" id="B1" programID="manual" phase="0" state="uuuuyyyyuuuuyyyy"/>
    <tlsState time="50.40" id="A0" programID="manual" phase="0" state="uuuuyyyyuuuuyyyy"/>
    <tlsState time="50.50" id="A1" programID="manual" phase="1" state="uuuurrrruuuurrrr"/>
    <tlsState time="50.60" id="B1" programID="manual" phase="1" state="uuuurrrruuuurrrr"/>
    <tlsState time="51.20" id="B0" programID="manual" phase="0" state="uuuuyyyyuuuuyyyy"/>
    <tlsState time="51.40" id="A0" programID="manual" phase="1" state="uuuurrrruuuurrrr"/>
    <tlsState time="51.50" id="A1" programID="manual" phase="2" state="GGggrrrrGGggrrrr"/>
    <tlsState time="51.60" id="B1" programID="manual" phase="2" state="GGggrrrrGGggrrrr"/>
    <tlsState time="52.20" id="B0" programID="manual" phase="1" state="uuuurrrruuuurrrr"/>
    <tlsState time="52.40" id="A0" programID="manual" phase="2" state="GGggrrrrGGggrrrr"/>
    <tlsState time="52.50" id="A1" programID="manual" phase="3" state="yyyyuuuuyyyyuuuu"/>
    <tlsState time="52.60" id="B1" programID="manual" phase="3" state="yyyyuuuuyyyyuuuu"/>
    <tlsState time="53.20" id="B0" programID="manual" phase="2" state="GGggrrrrGGggrrrr"/>
    <tlsState time="53.50" id="A1" programID="manual" phase="4" state="rrrruuuurrrruuuu"/>
    <tlsState time="53.60" id="B1" programID="manual" phase="4" state="rrrruuuurrrruuuu"/>
    <tlsState time="54.20" id="B0" programID="manual" phase="3" state="yyyyuuuuyyyyuuuu"/>
    <tlsState time="54.50" id="A1" programID="manual" phase="5" state="rrrrGGggrrrrGGgg"/>
    <tlsState time="54.60" id="B1" programID="manual" phase="5" state="rrrrGGggrrrrGGgg"/>
    <tlsState time="55.20" id="B0" programID="manual" phase="4" state="rrrruuuurrrruuuu"/>
    <tlsState time="55.60" id="B1" programID="manual" phase="0" state="uuuuyyyyuuuuyyyy"/>
    <tlsState time="56.20" id="B0" programID="manual" phase="5" state="rrrrGGggrrrrGGgg"/>
    <tlsState time="56.50" id="A1" programID="manual" phase="0" state="uuuuyyyyuuuuyyyy"/>
    <tlsState time="56.60" id="B1" programID="manual" phase="1" state="uuuurrrruuuurrrr"/>
    <tlsState time="57.00" id="A0" programID="manual" phase="3" state="yyyyuuuuyyyyuuuu"/>
    <tlsState time="57.50" id="A1" programID="manual" phase="1" state="uuuurrrruuuurrrr"/>
    <tlsState time="57.60" id="B1" programID="manual" phase="2" state="GGggrrrrGGggrrrr"/>
    <tlsState time="58.00" id="A0" programID="manual" phase="4" state="rrrruuuurrrruuuu"/>
    <tlsState time="58.50" id="A1" programID="manual" phase="2" state="GGggrrrrGGggrrrr"/>
    <tlsState time="58.60" id="B1" programID="manual" phase="3" state="yyyyuuuuyyyyuuuu"/>
    <tlsState time="59.00" id="A0" programID="manual" phase="5" state="rrrrGGggrrrrGGgg"/>
    <tlsState time="59.50" id="A1" programID="manual" phase="3" state="yyyyuuuuyyyyuuuu"/>
    <tlsState time="59.60" id="B1" programID="manual" phase="4" state="rrrruuuurrrruuuu"/>
    <tlsState time="59.70" id="B0" programID="manual" phase="0" state="uuuuyyyyuuuuyyyy"/>
    <tlsState time="60.50" id="A1" programID="manual" phase="4" state="rrrruuuurrrruuuu"/>
    <tlsState time="60.60" id="B1" programID="manual" phase="5" state="rrrrGGggrrrrGGgg"/>
    <tlsState time="60.70" id="B0" programID="manual" phase="1" state="uuuurrrruuuurrrr"/>
    <tlsState time="61.50" id="A1" programID="manual" phase="5" state="rrrrGGggrrrrGGgg"/>
    <tlsState time="61.60" id="B1" programID="manual" phase="0" state="uuuuyyyyuuuuyyyy"/>
    <tlsState time="61.70" id="B0" programID="manual" phase="2" state="GGggrrrrGGggrrrr"/>
    <tlsState time="62.60" id="B1" programID="manual" phase="1" state="uuuurrrruuuurrrr"/>
    <tlsState time="62.70" id="A0" programID="manual" phase="0" state="uuuuyyyyuuuuyyyy"/>
    <tlsState time="62.70" id="B0" programID="manual" phase="3" state="yyyyuuuuyyyyuuuu"/>
    <tlsState time="63.60" id="B1" programID="manual" phase="2" state="GGggrrrrGGggrrrr"/>
    <tlsState time="63.70" id="A0" programID="manual" phase="1" state="uuuurrrruuuurrrr"/>
    <tlsState time="63.70" id="B0" programID="manual" phase="4" state="rrrruuuurrrruuuu"/>
    <tlsState time="64.60" id="B1" programID="manual" phase="3" state="yyyyuuuuyyyyuuuu"/>
    <tlsState time="64.70" id="A0" programID="manual" phase="2" state="GGggrrrrGGggrrrr"/>
    <tlsState time="64.70" id="B0" programID="manual" phase="5" state="rrrrGGggrrrrGGgg"/>
    <tlsState time="65.60" id="B1" programID="manual" phase="4" state="rrrruuuurrrruuuu"/>
    <tlsState time="65.70" id="A0" programID="manual" phase="3" state="yyyyuuuuyyyyuuuu"/>
    <tlsState time="66.60" id="B1" programID="manual" phase="5" state="rrrrGGggrrrrGGgg"/>
    <tlsState time="66.70" id="A0" programID="manual" phase="4" state="rrrruuuurrrruuuu"/>
    <tlsState time="66.90" id="A1" programID="manual" phase="0" state="uuuuyyyyuuuuyyyy"/>
    <tlsState time="67.60" id="B1" programID="manual" phase="0" state="uuuuyyyyuuuuyyyy"/>
    <tlsState time="67.70" id="A0" programID="manual" phase="5" state="rrrrGGggrrrrGGgg"/>
    <tlsState time="67.70" id="B0" programID="manual" phase="0" state="uuuuyyyyuuuuyyyy"/>
    <tlsState time="67.90" id="A1" programID="manual" phase="1" state="uuuurrrruuuurrrr"/>
    <tlsState time="68.60" id="B1" programID="manual" phase="1" state="uuuurrrruuuurrrr"/>
    <tlsState time="68.70" id="B0" programID="manual" phase="1" state="uuuurrrruuuurrrr"/>
    <tlsState time="68.90" id="A1" programID="manual" phase="2" state="GGggrrrrGGggrrrr"/>
    <tlsState time="69.60" id="B1" programID="manual" phase="2" state="GGggrrrrGGggrrrr"/>
    <tlsState time="69.70" id="B0" programID="manual" phase="2" state="GGggrrrrGGggrrrr"/>
    <tlsState time="70.60" id="B1" programID="manual" phase="3" state="yyyyuuuuyyyyuuuu"/>
    <tlsState time="70.70" id="B0" programID="manual" phase="3" state="yyyyuuuuyyyyuuuu"/>
    <tlsState time="71.60" id="B1" programID="manual" phase="4" state="rrrruuuurrrruuuu"/>
    <tlsState time="71.70" id="B0" programID="manual" phase="4" state="rrrruuuurrrruuuu"/>
    <tlsState time="72.60" id="B1" programID="manual" phase="5" state="rrrrGGggrrrrGGgg"/>
    <tlsState time="72.70" id="B0" programID="manual" phase="5" state="rrrrGGggrrrrGGgg"/>
    <tlsState time="73.70" id="B0" programID="manual" phase="0" state="uuuuyyyyuuuuyyyy"/>
    <tlsState time="74.70" id="A0" programID="manual" phase="0" state="uuuuyyyyuuuuyyyy"/>
    <tlsState time="74.70" id="A1" programID="manual" phase="3" state="yyyyuuuuyyyyuuuu"/>
    <tlsState time="74.70" id="B0" programID="manual" phase="1" state="uuuurrrruuuurrrr"/>
    <tlsState time="75.70" id="A0" programID="manual" phase="1" state="uuuurrrruuuurrrr"/>
    <tlsState time="75.70" id="A1" programID="manual" phase="4" state="rrrruuuurrrruuuu"/>
    <tlsState time="75.70" id="B0" programID="manual" phase="2" state="GGggrrrrGGggrrrr"/>
    <tlsState time="76.70" id="A0" programID="manual" phase="2" state="GGggrrrrGGggrrrr"/>
    <tlsState time="76.70" id="A1" programID="manual" phase="5" state="rrrrGGggrrrrGGgg"/>
    <tlsState time="76.70" id="B0" programID="manual" phase="3" state="yyyyuuuuyyyyuuuu"/>
    <tlsState time="76.90" id="B1" programID="manual" phase="0" state="uuuuyyyyuuuuyyyy"/>
    <tlsState time="77.70" id="A1" programID="manual" phase="0" state="uuuuyyyyuuuuyyyy"/>
    <tlsState time="77.70" id="B0" programID="manual" phase="4" state="rrrruuuurrrruuuu"/>
    <tlsState time="77.90" id="B1" programID="manual" phase="1" state="uuuurrrruuuurrrr"/>
    <tlsState time="78.70" id="A0" programID="manual" phase="3" state="yyyyuuuuyyyyuuuu"/>
    <tlsState time="78.70" id="A1" programID="manual" phase="1" state="uuuurrrruuuurrrr"/>
    <tlsState time="78.70" id="B0" programID="manual" phase="5" state="rrrrGGggrrrrGGgg"/>
    <tlsState time="78.90" id="B1" programID="manual" phase="2" state="GGggrrrrGGggrrrr"/>
    <tlsState time="79.70" id="A0" programID="manual" phase="4" state="rrrruuuurrrruuuu"/>
    <tlsState time="79.70" id="A1" programID="manual" phase="2" state="GGggrrrrGGggrrrr"/>
    <tlsState time="80.70" id="A0" programID="manual" phase="5" state="rrrrGGggrrrrGGgg"/>
    <tlsState time="80.70" id="A1" programID="manual" phase="3" state="yyyyuuuuyyyyuuuu"/>
    <tlsState time="80.90" id="B1" programID="manual" phase="3" state="yyyyuuuuyyyyuuuu"/>
    <tlsState time="81.70" id="A1" programID="manual" phase="4" state="rrrruuuurrrruuuu"/>
    <tlsState time="81.90" id="B1" programID="manual" phase="4" state="rrrruuuurrrruuuu"/>
    <tlsState time="82.00" id="left0" programID="0" phase="1" state="y"/>
    <tlsState time="82.00" id="bottom0" programID="0" phase="1" state="y"/>
    <tlsState time="82.00" id="bottom1" programID="0" phase="1" state="y"/>
    <tlsState time="82.00" id="top0" programID="0" phase="1" state="y"/>
    <tlsState time="82.00" id="top1" programID="0" phase="1" state="y"/>
    <tlsState time="82.00" id="right1" programID="0" phase="1" state="y"/>
    <tlsState time="82.00" id="left1" programID="0" phase="1" state="y"/>
    <tlsState time="82.00" id="right0" programID="0" phase="1" state="y"/>
    <tlsState time="82.20" id="B0" programID="manual" phase="0" state="uuuuyyyyuuuuyyyy"/>
    <tlsState time="82.70" id="A1" programID="manual" phase="5" state="rrrrGGggrrrrGGgg"/>
    <tlsState time="82.90" id="B1" programID="manual" phase="5" state="rrrrGGggrrrrGGgg"/>
    <tlsState time="83.20" id="B0" programID="manual" phase="1" state="uuuurrrruuuurrrr"/>
    <tlsState time="83.70" id="A0" programID="manual" phase="0" state="uuuuyyyyuuuuyyyy"/>
    <tlsState time="84.20" id="B0" programID="manual" phase="2" state="GGggrrrrGGggrrrr"/>
    <tlsState time="84.70" id="A0" programID="manual" phase="1" state="uuuurrrruuuurrrr"/>
    <tlsState time="85.00" id="left0" programID="0" phase="2" state="r"/>
    <tlsState time="85.00" id="bottom0" programID="0" phase="2" state="r"/>
    <tlsState time="85.00" id="bottom1" programID="0" phase="2" state="r"/>
    <tlsState time="85.00" id="top0" programID="0" phase="2" state="r"/>
    <tlsState time="85.00" id="top1" programID="0" phase="2" state="r"/>
    <tlsState time="85.00" id="right1" programID="0" phase="2" state="r"/>
    <tlsState time="85.00" id="left1" programID="0" phase="2" state="r"/>
    <tlsState time="85.00" id="right0" programID="0" phase="2" state="r"/>
    <tlsState time="85.70" id="A0" programID="manual" phase="2" state="GGggrrrrGGggrrrr"/>
    <tlsState time="86.70" id="A0" programID="manual" phase="3" state="yyyyuuuuyyyyuuuu"/>
    <tlsState time="87.30" id="B1" programID="manual" phase="0" state="uuuuyyyyuuuuyyyy"/>
    <tlsState time="87.70" id="A0" programID="manual" phase="4" state="rrrruuuurrrruuuu"/>
    <tlsState time="88.30" id="B1" programID="manual" phase="1" state="uuuurrrruuuurrrr"/>
    <tlsState time="88.70" id="A0" programID="manual" phase="5" state="rrrrGGggrrrrGGgg"/>
    <tlsState time="89.30" id="B1" programID="manual" phase="2" state="GGggrrrrGGggrrrr"/>
    <tlsState time="90.00" id="left0" programID="0" phase="0" state="G"/>
    <tlsState time="90.00" id="top1" programID="0" phase="0" state="G"/>
    <tlsState time="90.00" id="bottom1" programID="0" phase="0" state="G"/>
    <tlsState time="90.00" id="bottom0" programID="0" phase="0" state="G"/>
    <tlsState time="90.00" id="top0" programID="0" phase="0" state="G"/>
    <tlsState time="90.00" id="right1" programID="0" phase="0" state="G"/>
    <tlsState time="90.00" id="right0" programID="0" phase="0" state="G"/>
    <tlsState time="90.00" id="left1" programID="0" phase="0" state="G"/>
    <tlsState time="92.80" id="B1" programID="manual" phase="3" state="yyyyuuuuyyyyuuuu"/>
    <tlsState time="93.20" id="B0" programID="manual" phase="3" state="yyyyuuuuyyyyuuuu"/>
    <tlsState time="93.80" id="B1" programID="manual" phase="4" state="rrrruuuurrrruuuu"/>
    <tlsState time="94.10" id="A0" programID="manual" phase="0" state="uuuuyyyyuuuuyyyy"/>
    <tlsState time="94.20" id="B0" programID="manual" phase="4" state="rrrruuuurrrruuuu"/>
    <tlsState time="94.80" id="B1" programID="manual" phase="5" state="rrrrGGggrrrrGGgg"/>
    <tlsState time="95.10" id="A0" programID="manual" phase="1" state="uuuurrrruuuurrrr"/>
    <tlsState time="95.20" id="B0" programID="manual" phase="5" state="rrrrGGggrrrrGGgg"/>
    <tlsState time="95.80" id="B1" programID="manual" phase="0" state="uuuuyyyyuuuuyyyy"/>
    <tlsState time="96.10" id="A0" programID="manual" phase="2" state="GGggrrrrGGggrrrr"/>
    <tlsState time="96.20" id="B0" programID="manual" phase="0" state="uuuuyyyyuuuuyyyy"/>
    <tlsState time="96.80" id="B1" programID="manual" phase="1" state="uuuurrrruuuurrrr"/>
    <tlsState time="97.10" id="A0" programID="manual" phase="3" state="yyyyuuuuyyyyuuuu"/>
    <tlsState time="97.20" id="B0" programID="manual" phase="1" state="uuuurrrruuuurrrr"/>
    <tlsState time="97.80" id="B1" programID="manual" phase="2" state="GGggrrrrGGggrrrr"/>
    <tlsState time="98.10" id="A0" programID="manual" phase="4" state="rrrruuuurrrruuuu"/>
    <tlsState time="98.20" id="B0" programID="manual" phase="2" state="GGggrrrrGGggrrrr"/>
    <tlsState time="99.10" id="A0" programID="manual" phase="5" state="rrrrGGggrrrrGGgg"/>
    <tlsState time="99.20" id="B0" programID="manual" phase="3" state="yyyyuuuuyyyyuuuu"/>
    <tlsState time="100.10" id="A0" programID="manual" phase="0" state="uuuuyyyyuuuuyyyy"/>
    <tlsState time="100.20" id="B0" programID="manual" phase="4" state="rrrruuuurrrruuuu"/>
    <tlsState time="101.10" id="A0" programID="manual" phase="1" state="uuuurrrruuuurrrr"/>
    <tlsState time="101.20" id="B0" programID="manual" phase="5" state="rrrrGGggrrrrGGgg"/>
    <tlsState time="101.40" id="B1" programID="manual" phase="3" state="yyyyuuuuyyyyuuuu"/>
    <tlsState time="102.10" id="A0" programID="manual" phase="2" state="GGggrrrrGGggrrrr"/>
    <tlsState time="102.40" id="B1" programID="manual" phase="4" state="rrrruuuurrrruuuu"/>
    <tlsState time="103.10" id="A0" programID="manual" phase="3" state="yyyyuuuuyyyyuuuu"/>
    <tlsState time="103.40" id="B1" programID="manual" phase="5" state="rrrrGGggrrrrGGgg"/>
    <tlsState time="104.10" id="A0" programID="manual" phase="4" state="rrrruuuurrrruuuu"/>
    <tlsState time="105.10" id="A0" programID="manual" phase="5" state="rrrrGGggrrrrGGgg"/>
    <tlsState time="105.80" id="A1" programID="manual" phase="0" state="uuuuyyyyuuuuyyyy"/>
    <tlsState time="106.10" id="A0" programID="manual" phase="0" state="uuuuyyyyuuuuyyyy"/>
    <tlsState time="106.60" id="B0" programID="manual" phase="0" state="uuuuyyyyuuuuyyyy"/>
    <tlsState time="106.80" id="A1" programID="manual" phase="1" state="uuuurrrruuuurrrr"/>
    <tlsState time="107.10" id="A0" programID="manual" phase="1" state="uuuurrrruuuurrrr"/>
    <tlsState time="107.60" id="B0" programID="manual" phase="1" state="uuuurrrruuuurrrr"/>
    <tlsState time="107.80" id="A1" programID="manual" phase="2" state="GGggrrrrGGggrrrr"/>
    <tlsState time="108.10" id="A0" programID="manual" phase="2" state="GGggrrrrGGggrrrr"/>
    <tlsState time="108.60" id="B0" programID="manual" phase="2" state="GGggrrrrGGggrrrr"/>
    <tlsState time="108.80" id="A1" programID="manual" phase="3" state="yyyyuuuuyyyyuuuu"/>
    <tlsState time="109.30" id="B1" programID="manual" phase="0" state="uuuuyyyyuuuuyyyy"/>
    <tlsState time="109.80" id="A1" programID="manual" phase="4" state="rrrruuuurrrruuuu"/>
    <tlsState time="110.30" id="B1" programID="manual" phase="1" state="uuuurrrruuuurrrr"/>
    <tlsState time="110.80" id="A1" programID="manual" phase="5" state="rrrrGGggrrrrGGgg"/>
    <tlsState time="111.30" id="B1" programID="manual" phase="2" state="GGggrrrrGGggrrrr"/>
    <tlsState time="111.70" id="A0" programID="manual" phase="3" state="yyyyuuuuyyyyuuuu"/>
    <tlsState time="111.80" id="A1" programID="manual" phase="0" state="uuuuyyyyuuuuyyyy"/>
    <tlsState time="112.30" id="B1" programID="manual" phase="3" state="yyyyuuuuyyyyuuuu"/>
    <tlsState time="112.70" id="A0" programID="manual" phase="4" state="rrrruuuurrrruuuu"/>
    <tlsState time="112.80" id="A1" programID="manual" phase="1" state="uuuurrrruuuurrrr"/>
    <tlsState time="113.30" id="B1" programID="manual" phase="4" state="rrrruuuurrrruuuu"/>
    <tlsState time="113.70" id="A0" programID="manual" phase="5" state="rrrrGGggrrrrGGgg"/>
    <tlsState time="113.80" id="A1" programID="manual" phase="2" state="GGggrrrrGGggrrrr"/>
    <tlsState time="114.00" id="B0" programID="manual" phase="3" state="yyyyuuuuyyyyuuuu"/>
    <tlsState time="114.30" id="B1" programID="manual" phase="5" state="rrrrGGggrrrrGGgg"/>
    <tlsState time="115.00" id="B0" programID="manual" phase="4" state="rrrruuuurrrruuuu"/>
    <tlsState time="116.00" id="B0" programID="manual" phase="5" state="rrrrGGggrrrrGGgg"/>
    <tlsState time="117.00" id="B0" programID="manual" phase="0" state="uuuuyyyyuuuuyyyy"/>
    <tlsState time="118.00" id="B0" programID="manual" phase="1" state="uuuurrrruuuurrrr"/>
    <tlsState time="118.30" id="B1" programID="manual" phase="0" state="uuuuyyyyuuuuyyyy"/>
    <tlsState time="119.00" id="B0" programID="manual" phase="2" state="GGggrrrrGGggrrrr"/>
    <tlsState time="119.30" id="B1" programID="manual" phase="1" state="uuuurrrruuuurrrr"/>
    <tlsState time="120.00" id="B0" programID="manual" phase="3" state="yyyyuuuuyyyyuuuu"/>
    <tlsState time="120.30" id="B1" programID="manual" phase="2" state="GGggrrrrGGggrrrr"/>
    <tlsState time="121.00" id="B0" programID="manual" phase="4" state="rrrruuuurrrruuuu"/>
    <tlsState time="121.30" id="B1" programID="manual" phase="3" state="yyyyuuuuyyyyuuuu"/>
    <tlsState time="121.90" id="A1" programID="manual" phase="3" state="yyyyuuuuyyyyuuuu"/>
    <tlsState time="122.00" id="B0" programID="manual" phase="5" state="rrrrGGggrrrrGGgg"/>
    <tlsState time="122.30" id="B1" programID="manual" phase="4" state="rrrruuuurrrruuuu"/>
    <tlsState time="122.40" id="A0" programID="manual" phase="0" state="uuuuyyyyuuuuyyyy"/>
    <tlsState time="122.90" id="A1" programID="manual" phase="4" state="rrrruuuurrrruuuu"/>
    <tlsState time="123.30" id="B1" programID="manual" phase="5" state="rrrrGGggrrrrGGgg"/>
    <tlsState time="123.40" id="A0" programID="manual" phase="1" state="uuuurrrruuuurrrr"/>
    <tlsState time="123.90" id="A1" programID="manual" phase="5" state="rrrrGGggrrrrGGgg"/>
    <tlsState time="124.40" id="A0" programID="manual" phase="2" state="GGggrrrrGGggrrrr"/>
    <tlsState time="126.80" id="B1" programID="manual" phase="0" state="uuuuyyyyuuuuyyyy"/>
    <tlsState time="127.80" id="B1" programID="manual" phase="1" state="uuuurrrruuuurrrr"/>
    <tlsState time="127.90" id="A0" programID="manual" phase="3" state="yyyyuuuuyyyyuuuu"/>
    <tlsState time="128.80" id="B1" programID="manual" phase="2" state="GGggrrrrGGggrrrr"/>
    <tlsState time="128.90" id="A0" programID="manual" phase="4" state="rrrruuuurrrruuuu"/>
    <tlsState time="129.80" id="B1" programID="manual" phase="3" state="yyyyuuuuyyyyuuuu"/>
    <tlsState time="129.90" id="A0" programID="manual" phase="5" state="rrrrGGggrrrrGGgg"/>
    <tlsState time="130.40" id="B0" programID="manual" phase="0" state="uuuuyyyyuuuuyyyy"/>
    <tlsState time="130.80" id="A1" programID="manual" phase="0" state="uuuuyyyyuuuuyyyy"/>
    <tlsState time="130.80" id="B1" programID="manual" phase="4" state="rrrruuuurrrruuuu"/>
    <tlsState time="131.40" id="B0" programID="manual" phase="1" state="uuuurrrruuuurrrr"/>
    <tlsState time="131.80" id="B1" programID="manual" phase="5" state="rrrrGGggrrrrGGgg"/>
    <tlsState time="131.80" id="A1" programID="manual" phase="1" state="uuuurrrruuuurrrr"/>
    <tlsState time="132.40" id="B0" programID="manual" phase="2" state="GGggrrrrGGggrrrr"/>
    <tlsState time="132.80" id="A1" programID="manual" phase="2" state="GGggrrrrGGggrrrr"/>
    <tlsState time="133.80" id="A1" programID="manual" phase="3" state="yyyyuuuuyyyyuuuu"/>
    <tlsState time="134.40" id="B0" programID="manual" phase="3" state="yyyyuuuuyyyyuuuu"/>
    <tlsState time="134.80" id="A1" programID="manual" phase="4" state="rrrruuuurrrruuuu"/>
    <tlsState time="135.40" id="B0" programID="manual" phase="4" state="rrrruuuurrrruuuu"/>
    <tlsState time="135.80" id="A1" programID="manual" phase="5" state="rrrrGGggrrrrGGgg"/>
    <tlsState time="136.40" id="B0" programID="manual" phase="5" state="rrrrGGggrrrrGGgg"/>
    <tlsState time="136.80" id="A1" programID="manual" phase="0" state="uuuuyyyyuuuuyyyy"/>
    <tlsState time="137.10" id="A0" programID="manual" phase="0" state="uuuuyyyyuuuuyyyy"/>
    <tlsState time="137.40" id="B0" programID="manual" phase="0" state="uuuuyyyyuuuuyyyy"/>
    <tlsState time="137.80" id="A1" programID="manual" phase="1" state="uuuurrrruuuurrrr"/>
    <tlsState time="138.10" id="A0" programID="manual" phase="1" state="uuuurrrruuuurrrr"/>
    <tlsState time="138.40" id="B0" programID="manual" phase="1" state="uuuurrrruuuurrrr"/>
    <tlsState time="138.80" id="A1" programID="manual" phase="2" state="GGggrrrrGGggrrrr"/>
    <tlsState time="139.10" id="A0" programID="manual" phase="2" state="GGggrrrrGGggrrrr"/>
    <tlsState time="139.40" id="B0" programID="manual" phase="2" state="GGggrrrrGGggrrrr"/>
    <tlsState time="140.10" id="A0" programID="manual" phase="3" state="yyyyuuuuyyyyuuuu"/>
    <tlsState time="140.40" id="B0" programID="manual" phase="3" state="yyyyuuuuyyyyuuuu"/>
    <tlsState time="141.10" id="A0" programID="manual" phase="4" state="rrrruuuurrrruuuu"/>
    <tlsState time="141.40" id="B0" programID="manual" phase="4" state="rrrruuuurrrruuuu"/>
    <tlsState time="142.10" id="A0" programID="manual" phase="5" state="rrrrGGggrrrrGGgg"/>
    <tlsState time="142.10" id="A1" programID="manual" phase="3" state="yyyyuuuuyyyyuuuu"/>
    <tlsState time="142.40" id="B0" programID="manual" phase="5" state="rrrrGGggrrrrGGgg"/>
    <tlsState time="143.10" id="A0" programID="manual" phase="0" state="uuuuyyyyuuuuyyyy"/>
    <tlsState time="143.10" id="A1" programID="manual" phase="4" state="rrrruuuurrrruuuu"/>
    <tlsState time="143.50" id="B1" programID="manual" phase="0" state="uuuuyyyyuuuuyyyy"/>
    <tlsState time="144.10" id="A0" programID="manual" phase="1" state="uuuurrrruuuurrrr"/>
    <tlsState time="144.10" id="A1" programID="manual" phase="5" state="rrrrGGggrrrrGGgg"/>
    <tlsState time="144.50" id="B1" programID="manual" phase="1" state="uuuurrrruuuurrrr"/>
    <tlsState time="145.10" id="A0" programID="manual" phase="2" state="GGggrrrrGGggrrrr"/>
    <tlsState time="145.50" id="B1" programID="manual" phase="2" state="GGggrrrrGGggrrrr"/>
    <tlsState time="146.50" id="B1" programID="manual" phase="3" state="yyyyuuuuyyyyuuuu"/>
    <tlsState time="147.50" id="B1" programID="manual" phase="4" state="rrrruuuurrrruuuu"/>
    <tlsState time="148.50" id="B1" programID="manual" phase="5" state="rrrrGGggrrrrGGgg"/>
    <tlsState time="149.10" id="A0" programID="manual" phase="3" state="yyyyuuuuyyyyuuuu"/>
    <tlsState time="149.40" id="B0" programID="manual" phase="0" state="uuuuyyyyuuuuyyyy"/>
    <tlsState time="150.10" id="A0" programID="manual" phase="4" state="rrrruuuurrrruuuu"/>
    <tlsState time="150.40" id="B0" programID="manual" phase="1" state="uuuurrrruuuurrrr"/>
    <tlsState time="151.10" id="A0" programID="manual" phase="5" state="rrrrGGggrrrrGGgg"/>
    <tlsState time="151.30" id="A1" programID="manual" phase="0" state="uuuuyyyyuuuuyyyy"/>
    <tlsState time="151.40" id="B0" programID="manual" phase="2" state="GGggrrrrGGggrrrr"/>
    <tlsState time="152.30" id="A1" programID="manual" phase="1" state="uuuurrrruuuurrrr"/>
    <tlsState time="153.30" id="A1" programID="manual" phase="2" state="GGggrrrrGGggrrrr"/>
    <tlsState time="154.70" id="B1" programID="manual" phase="0" state="uuuuyyyyuuuuyyyy"/>
    <tlsState time="155.70" id="B1" programID="manual" phase="1" state="uuuurrrruuuurrrr"/>
    <tlsState time="156.70" id="B1" programID="manual" phase="2" state="GGggrrrrGGggrrrr"/>
    <tlsState time="157.30" id="A1" programID="manual" phase="3" state="yyyyuuuuyyyyuuuu"/>
    <tlsState time="157.70" id="B1" programID="manual" phase="3" state="yyyyuuuuyyyyuuuu"/>
    <tlsState time="158.30" id="A1" programID="manual" phase="4" state="rrrruuuurrrruuuu"/>
    <tlsState time="158.60" id="B0" programID="manual" phase="3" state="yyyyuuuuyyyyuuuu"/>
    <tlsState time="158.70" id="B1" programID="manual" phase="4" state="rrrruuuurrrruuuu"/>
    <tlsState time="159.30" id="A1" programID="manual" phase="5" state="rrrrGGggrrrrGGgg"/>
    <tlsState time="159.60" id="B0" programID="manual" phase="4" state="rrrruuuurrrruuuu"/>
    <tlsState time="159.70" id="B1" programID="manual" phase="5" state="rrrrGGggrrrrGGgg"/>
    <tlsState time="160.60" id="B0" programID="manual" phase="5" state="rrrrGGggrrrrGGgg"/>
    <tlsState time="160.70" id="B1" programID="manual" phase="0" state="uuuuyyyyuuuuyyyy"/>
    <tlsState time="161.70" id="B1" programID="manual" phase="1" state="uuuurrrruuuurrrr"/>
    <tlsState time="162.70" id="B1" programID="manual" phase="2" state="GGggrrrrGGggrrrr"/>
    <tlsState time="163.10" id="A0" programID="manual" phase="0" state="uuuuyyyyuuuuyyyy"/>
    <tlsState time="164.10" id="A0" programID="manual" phase="1" state="uuuurrrruuuurrrr"/>
    <tlsState time="165.10" id="A0" programID="manual" phase="2" state="GGggrrrrGGggrrrr"/>
    <tlsState time="166.10" id="A0" programID="manual" phase="3" state="yyyyuuuuyyyyuuuu"/>
    <tlsState time="166.60" id="B0" programID="manual" phase="0" state="uuuuyyyyuuuuyyyy"/>
    <tlsState time="167.10" id="A0" programID="manual" phase="4" state="rrrruuuurrrruuuu"/>
    <tlsState time="167.60" id="B0" programID="manual" phase="1" state="uuuurrrruuuurrrr"/>
    <tlsState time="168.10" id="A0" programID="manual" phase="5" state="rrrrGGggrrrrGGgg"/>
    <tlsState time="168.60" id="B0" programID="manual" phase="2" state="GGggrrrrGGggrrrr"/>
    <tlsState time="168.80" id="B1" programID="manual" phase="3" state="yyyyuuuuyyyyuuuu"/>
    <tlsState time="169.60" id="B0" programID="manual" phase="3" state="yyyyuuuuyyyyuuuu"/>
    <tlsState time="169.80" id="B1" programID="manual" phase="4" state="rrrruuuurrrruuuu"/>
    <tlsState time="170.60" id="B0" programID="manual" phase="4" state="rrrruuuurrrruuuu"/>
    <tlsState time="170.80" id="B1" programID="manual" phase="5" state="rrrrGGggrrrrGGgg"/>
    <tlsState time="171.10" id="A0" programID="manual" phase="0" state="uuuuyyyyuuuuyyyy"/>
    <tlsState time="171.60" id="B0" programID="manual" phase="5" state="rrrrGGggrrrrGGgg"/>
    <tlsState time="172.00" id="left0" programID="0" phase="1" state="y"/>
    <tlsState time="172.00" id="bottom0" programID="0" phase="1" state="y"/>
    <tlsState time="172.00" id="bottom1" programID="0" phase="1" state="y"/>
    <tlsState time="172.00" id="top0" programID="0" phase="1" state="y"/>
    <tlsState time="172.00" id="top1" programID="0" phase="1" state="y"/>
    <tlsState time="172.00" id="right1" programID="0" phase="1" state="y"/>
    <tlsState time="172.00" id="left1" programID="0" phase="1" state="y"/>
    <tlsState time="172.00" id="right0" programID="0" phase="1" state="y"/>
    <tlsState time="172.10" id="A0" programID="manual" phase="1" state="uuuurrrruuuurrrr"/>
    <tlsState time="172.60" id="B0" programID="manual" phase="0" state="uuuuyyyyuuuuyyyy"/>
    <tlsState time="173.10" id="A0" programID="manual" phase="2" state="GGggrrrrGGggrrrr"/>
    <tlsState time="173.60" id="B0" programID="manual" phase="1" state="uuuurrrruuuurrrr"/>
    <tlsState time="174.10" id="A0" programID="manual" phase="3" state="yyyyuuuuyyyyuuuu"/>
    <tlsState time="174.60" id="B0" programID="manual" phase="2" state="GGggrrrrGGggrrrr"/>
    <tlsState time="175.00" id="left0" programID="0" phase="2" state="r"/>
    <tlsState time="175.00" id="bottom0" programID="0" phase="2" state="r"/>
    <tlsState time="175.00" id="bottom1" programID="0" phase="2" state="r"/>
    <tlsState time="175.00" id="top0" programID="0" phase="2" state="r"/>
    <tlsState time="175.00" id="top1" programID="0" phase="2" state="r"/>
    <tlsState time="175.00" id="right1" programID="0" phase="2" state="r"/>
    <tlsState time="175.00" id="left1" programID="0" phase="2" state="r"/>
    <tlsState time="175.00" id="right0" programID="0" phase="2" state="r"/>
    <tlsState time="175.10" id="A0" programID="manual" phase="4" state="rrrruuuurrrruuuu"/>
    <tlsState time="175.30" id="A1" programID="manual" phase="0" state="uuuuyyyyuuuuyyyy"/>
    <tlsState time="176.10" id="A0" programID="manual" phase="5" state="rrrrGGggrrrrGGgg"/>
    <tlsState time="176.30" id="A1" programID="manual" phase="1" state="uuuurrrruuuurrrr"/>
    <tlsState time="177.30" id="A1" programID="manual" phase="2" state="GGggrrrrGGggrrrr"/>
    <tlsState time="177.90" id="B0" programID="manual" phase="3" state="yyyyuuuuyyyyuuuu"/>
    <tlsState time="178.30" id="A1" programID="manual" phase="3" state="yyyyuuuuyyyyuuuu"/>
    <tlsState time="178.80" id="B1" programID="manual" phase="0" state="uuuuyyyyuuuuyyyy"/>
    <tlsState time="178.90" id="B0" programID="manual" phase="4" state="rrrruuuurrrruuuu"/>
    <tlsState time="179.30" id="A1" programID="manual" phase="4" state="rrrruuuurrrruuuu"/>
    <tlsState time="179.80" id="B1" programID="manual" phase="1" state="uuuurrrruuuurrrr"/>
    <tlsState time="179.90" id="B0" programID="manual" phase="5" state="rrrrGGggrrrrGGgg"/>
</tlsStates>
